MANIFEST.in
README.rst
VERSION
setup.py
scripts/scm-download-taxa.sh
src/scm/__init__.py
src/scm/main.py
src/scm/blast_filter/__init__.py
src/scm/blast_filter/command.py
src/scm/lca/__init__.py
src/scm/lca/command.py
src/scm/report/__init__.py
src/scm/report/command.py
src/scm/report/common.py
src/scm/report/interactive.py
src/scm/report/static.py
src/scm/ui/__init__.py
src/scm/ui/utils.py
src/scm/workflow/__init__.py
src/scm/workflow/command.py
src/single_cell_m.egg-info/PKG-INFO
src/single_cell_m.egg-info/SOURCES.txt
src/single_cell_m.egg-info/dependency_links.txt
src/single_cell_m.egg-info/entry_points.txt
src/single_cell_m.egg-info/requires.txt
src/single_cell_m.egg-info/top_level.txt